{"stats":{"minecraft:used":{"minecraft:moss_carpet":2,"minecraft:chest":126,"minecraft:shield":65,"minecraft:stone":6063,"minecraft:iron_sword":1127,"minecraft:rotten_flesh":78,"minecraft:sculk_sensor":5,"minecraft:soul_sand":9,"minecraft:mutton":3,"minecraft:nether_bricks":35,"minecraft:carrot":135,"minecraft:tuff":9,"minecraft:obsidian":30,"minecraft:azure_bluet":1,"minecraft:milk_bucket":1,"minecraft:glass":108,"minecraft:lava_bucket":20,"minecraft:coal_ore":49,"minecraft:grass_block":69,"minecraft:iron_helmet":1,"minecraft:stone_brick_stairs":3,"minecraft:stone_bricks":209,"minecraft:deepslate_diamond_ore":36,"minecraft:redstone_lamp":1,"minecraft:bow":78,"minecraft:dark_oak_boat":4,"minecraft:sweet_berries":85,"minecraft:oak_sapling":6,"minecraft:furnace":4,"minecraft:egg":4,"minecraft:potato":7,"minecraft:diorite":1,"minecraft:oak_planks":25,"minecraft:stone_pickaxe":43,"minecraft:powered_rail":37,"minecraft:wither_skeleton_skull":3,"minecraft:dark_oak_sign":3,"minecraft:blackstone":32,"minecraft:wooden_pickaxe":3,"minecraft:composter":11,"minecraft:diamond_axe":2877,"minecraft:white_wool":1,"minecraft:golden_apple":5,"minecraft:dark_oak_trapdoor":8,"minecraft:sand":18,"minecraft:blast_furnace":4,"minecraft:crossbow":37,"minecraft:stone_brick_wall":104,"minecraft:dripstone_block":2,"minecraft:sticky_piston":9,"minecraft:lever":17,"minecraft:dark_oak_log":31,"minecraft:bread":212,"minecraft:lectern":365,"minecraft:deepslate":60,"minecraft:gravel":63,"minecraft:soul_lantern":4,"minecraft:diamond_sword":5528,"minecraft:wooden_sword":15,"minecraft:andesite":28,"minecraft:oak_boat":9,"minecraft:bone_meal":306,"minecraft:experience_bottle":2,"minecraft:oak_fence":10,"minecraft:rose_bush":1,"minecraft:flint_and_steel":11,"minecraft:cooked_chicken":2,"minecraft:netherrack":449,"minecraft:oak_door":1,"minecraft:anvil":1,"minecraft:torch":145,"minecraft:dirt":103,"minecraft:hopper":8,"minecraft:nether_quartz_ore":2,"minecraft:diamond_helmet":1,"minecraft:granite":5,"minecraft:mossy_cobblestone_stairs":1,"minecraft:iron_hoe":460,"minecraft:iron_block":172,"minecraft:iron_axe":584,"minecraft:iron_boots":3,"minecraft:golden_carrot":3,"minecraft:basalt":726,"minecraft:beef":3,"minecraft:iron_trapdoor":1,"minecraft:goat_horn":1,"minecraft:netherite_pickaxe":83631,"minecraft:minecart":9,"minecraft:cooked_beef":123,"minecraft:observer":12,"minecraft:cobbled_deepslate":99,"minecraft:cooked_mutton":88,"minecraft:water_bucket":148,"minecraft:cobblestone_stairs":1,"minecraft:baked_potato":14,"minecraft:spruce_sign":45,"minecraft:cauldron":8,"minecraft:beacon":2,"minecraft:fletching_table":3,"minecraft:cobblestone_slab":10,"minecraft:polished_blackstone_bricks":9,"minecraft:mossy_cobblestone":1,"minecraft:rail":36,"minecraft:crafting_table":17,"minecraft:oak_slab":5,"minecraft:spruce_log":7,"minecraft:oak_log":8,"minecraft:piston":9,"minecraft:diamond_pickaxe":34567,"minecraft:apple":9,"minecraft:diamond_shovel":23381,"minecraft:cracked_polished_blackstone_bricks":1,"minecraft:iron_pickaxe":477,"minecraft:suspicious_stew":2,"minecraft:stone_slab":459,"minecraft:spruce_trapdoor":12,"minecraft:stone_axe":150,"minecraft:pink_petals":8,"minecraft:cobblestone":617,"minecraft:porkchop":1,"minecraft:white_banner":5,"minecraft:cooked_porkchop":125,"minecraft:bucket":168,"minecraft:glass_pane":1,"minecraft:brush":8,"minecraft:dandelion":1,"minecraft:kelp":3,"minecraft:diamond_leggings":1,"minecraft:gray_wool":9,"minecraft:sculk_vein":1},"minecraft:killed":{"minecraft:zombified_piglin":8,"minecraft:witch":3,"minecraft:spider":48,"minecraft:wither":1,"minecraft:skeleton":114,"minecraft:chicken":2,"minecraft:piglin_brute":3,"minecraft:magma_cube":92,"minecraft:piglin":26,"minecraft:pig":22,"minecraft:zombie_villager":2,"minecraft:creeper":33,"minecraft:sheep":31,"minecraft:trader_llama":2,"minecraft:pillager":1543,"minecraft:donkey":3,"minecraft:zombie":123,"minecraft:blaze":1638,"minecraft:cow":38,"minecraft:vindicator":1,"minecraft:slime":20,"minecraft:phantom":1,"minecraft:bat":1,"minecraft:hoglin":2,"minecraft:wither_skeleton":234,"minecraft:villager":1},"minecraft:crafted":{"minecraft:smooth_stone":8,"minecraft:oak_planks":3048,"minecraft:cobblestone_slab":6,"minecraft:cooked_chicken":2,"minecraft:stone":6,"minecraft:lever":1,"minecraft:diamond_shovel":2,"minecraft:bookshelf":2,"minecraft:cooked_mutton":22,"minecraft:glass":69,"minecraft:hopper":8,"minecraft:diamond_helmet":1,"minecraft:diamond_leggings":1,"minecraft:iron_boots":5,"minecraft:beacon":1,"minecraft:chest":126,"minecraft:netherite_upgrade_smithing_template":4,"minecraft:stone_bricks":384,"minecraft:oak_fence":12,"minecraft:oak_slab":12,"minecraft:emerald":275,"minecraft:cooked_porkchop":1,"minecraft:diamond_axe":1,"minecraft:crafting_table":12,"minecraft:spruce_planks":256,"minecraft:iron_helmet":4,"minecraft:wooden_pickaxe":1,"minecraft:baked_potato":14,"minecraft:fletching_table":2,"minecraft:gold_block":9,"minecraft:stone_brick_stairs":4,"minecraft:lectern":1,"minecraft:iron_chestplate":5,"minecraft:dark_oak_slab":12,"minecraft:book":10,"minecraft:paper":39,"minecraft:diamond_pickaxe":6,"minecraft:shield":3,"minecraft:stick":8976,"minecraft:stone_slab":744,"minecraft:iron_ingot":1940,"minecraft:iron_pickaxe":2,"minecraft:iron_block":200,"minecraft:gold_ingot":88,"minecraft:netherite_ingot":1,"minecraft:composter":2,"minecraft:wooden_sword":1,"minecraft:oak_door":3,"minecraft:stone_brick_wall":180,"minecraft:iron_nugget":1,"minecraft:furnace":5,"minecraft:blast_furnace":2,"minecraft:piston":1,"minecraft:dark_oak_sign":3,"minecraft:bone_meal":384,"minecraft:diamond_block":14,"minecraft:glass_pane":16,"minecraft:flint_and_steel":1,"minecraft:iron_axe":5,"minecraft:iron_hoe":6,"minecraft:stone_pickaxe":1,"minecraft:diamond_boots":1,"minecraft:netherite_scrap":4,"minecraft:dark_oak_planks":2568,"minecraft:lead":2,"minecraft:minecart":6,"minecraft:wheat":450,"minecraft:cooked_beef":24,"minecraft:netherite_pickaxe":1,"minecraft:diamond_sword":4,"minecraft:iron_sword":7,"minecraft:bucket":5,"minecraft:stone_axe":2,"minecraft:enchanted_book":11,"minecraft:air":0,"minecraft:bread":150,"minecraft:oak_boat":9,"minecraft:iron_leggings":3,"minecraft:anvil":1,"minecraft:diamond_chestplate":1},"minecraft:broken":{"minecraft:golden_helmet":1,"minecraft:iron_boots":3,"minecraft:iron_chestplate":2,"minecraft:iron_leggings":1,"minecraft:iron_sword":3,"minecraft:bow":1,"minecraft:iron_hoe":1,"minecraft:shield":1,"minecraft:iron_axe":1,"minecraft:iron_pickaxe":1,"minecraft:iron_helmet":3},"minecraft:custom":{"minecraft:interact_with_crafting_table":169,"minecraft:bell_ring":2,"minecraft:leave_game":47,"minecraft:time_since_death":172582,"minecraft:sprint_one_cm":9818674,"minecraft:damage_blocked_by_shield":3166,"minecraft:drop":316,"minecraft:talked_to_villager":665,"minecraft:play_time":2347153,"minecraft:deaths":98,"minecraft:jump":41632,"minecraft:enchant_item":15,"minecraft:walk_on_water_one_cm":126889,"minecraft:interact_with_furnace":288,"minecraft:traded_with_villager":288,"minecraft:sleep_in_bed":40,"minecraft:open_enderchest":1,"minecraft:damage_dealt":434901,"minecraft:interact_with_beacon":5,"minecraft:crouch_one_cm":561276,"minecraft:horse_one_cm":69929,"minecraft:interact_with_smithing_table":1,"minecraft:interact_with_anvil":12,"minecraft:mob_kills":4049,"minecraft:inspect_hopper":2,"minecraft:climb_one_cm":788,"minecraft:walk_one_cm":6272444,"minecraft:sneak_time":143689,"minecraft:walk_under_water_one_cm":265901,"minecraft:boat_one_cm":1015689,"minecraft:interact_with_blast_furnace":191,"minecraft:total_world_time":2347153,"minecraft:tune_noteblock":1,"minecraft:raid_trigger":6,"minecraft:time_since_rest":2167,"minecraft:damage_taken":58720,"minecraft:damage_absorbed":160,"minecraft:swim_one_cm":217832,"minecraft:fly_one_cm":9281959,"minecraft:open_chest":1596,"minecraft:fall_one_cm":1134478},"minecraft:dropped":{"minecraft:iron_sword":1,"minecraft:soul_sand":1,"minecraft:cooked_beef":34,"minecraft:oak_log":77,"minecraft:diamond":59,"minecraft:netherite_upgrade_smithing_template":1,"minecraft:dark_oak_slab":1,"minecraft:crossbow":15,"minecraft:leather":1,"minecraft:creeper_banner_pattern":1,"minecraft:saddle":1,"minecraft:rail":1,"minecraft:flint":1,"minecraft:cobblestone_stairs":8,"minecraft:emerald":36,"minecraft:cracked_polished_blackstone_bricks":2,"minecraft:dirt":194,"minecraft:dark_oak_log":2,"minecraft:crimson_roots":4,"minecraft:netherite_boots":2,"minecraft:gold_nugget":5,"minecraft:polished_blackstone_bricks":12,"minecraft:dark_oak_boat":1,"minecraft:white_wool":6,"minecraft:gold_ingot":1,"minecraft:bone":298,"minecraft:oak_door":4,"minecraft:gravel":238,"minecraft:blackstone":1,"minecraft:golden_chestplate":1,"minecraft:cobbled_deepslate":39,"minecraft:pointed_dripstone":2,"minecraft:rotten_flesh":65,"minecraft:oak_planks":70,"minecraft:cooked_mutton":2,"minecraft:leather_chestplate":1,"minecraft:gunpowder":7,"minecraft:coal_ore":1,"minecraft:chest":2,"minecraft:basalt":1,"minecraft:arrow":2,"minecraft:netherrack":1608,"minecraft:egg":2,"minecraft:golden_boots":1,"minecraft:bread":1,"minecraft:oak_slab":6,"minecraft:netherite_pickaxe":4,"minecraft:wheat_seeds":14,"minecraft:golden_helmet":1,"minecraft:minecart":2,"minecraft:book":10,"minecraft:feather":2,"minecraft:cobblestone":347,"minecraft:observer":7,"minecraft:granite":21,"minecraft:grass_block":14,"minecraft:coal":5,"minecraft:stick":7,"minecraft:golden_apple":1,"minecraft:oxeye_daisy":2,"minecraft:milk_bucket":1,"minecraft:diorite":16,"minecraft:iron_leggings":3,"minecraft:oak_stairs":2,"minecraft:wither_rose":4,"minecraft:white_banner":2,"minecraft:iron_shovel":1,"minecraft:chainmail_leggings":2,"minecraft:string":31,"minecraft:pink_petals":11,"minecraft:bucket":1,"minecraft:redstone":9,"minecraft:dandelion":1,"minecraft:spruce_sapling":1,"minecraft:stone_brick_slab":1,"minecraft:sweet_berries":5,"minecraft:stone_sword":28,"minecraft:blaze_rod":2,"minecraft:dark_oak_sign":1,"minecraft:smooth_stone_slab":1,"minecraft:sticky_piston":6,"minecraft:deepslate":1,"minecraft:tuff":6,"minecraft:sculk_sensor":4,"minecraft:wither_skeleton_skull":1,"minecraft:light_gray_wool":1,"minecraft:stone_slab":120,"minecraft:diamond_sword":2,"minecraft:stone":1555,"minecraft:shield":1,"minecraft:diamond_pickaxe":7,"minecraft:iron_chestplate":1,"minecraft:andesite":24,"minecraft:mossy_stone_bricks":1,"minecraft:golden_leggings":1,"minecraft:oak_boat":1,"minecraft:oak_sapling":22,"minecraft:stone_bricks":1,"minecraft:spider_eye":31,"minecraft:bow":3,"minecraft:raw_gold":5,"minecraft:magma_cream":3},"minecraft:picked_up":{"minecraft:iron_chestplate":60,"minecraft:nether_brick_fence":33,"minecraft:lead":22,"minecraft:stone_slab":161,"minecraft:diamond_sword":72,"minecraft:oak_stairs":2,"minecraft:wither_rose":8,"minecraft:enchanted_book":2,"minecraft:stone_brick_stairs":3,"minecraft:string":236,"minecraft:raw_copper":824,"minecraft:smooth_stone_slab":1,"minecraft:iron_leggings":28,"minecraft:sticky_piston":24,"minecraft:diamond_leggings":38,"minecraft:gold_nugget":268,"minecraft:cobbled_deepslate":546,"minecraft:spruce_planks":64,"minecraft:bucket":17,"minecraft:white_tulip":2,"minecraft:rose_bush":1,"minecraft:cobblestone_slab":7,"minecraft:iron_pickaxe":5,"minecraft:netherite_upgrade_smithing_template":2,"minecraft:iron_boots":52,"minecraft:furnace":4,"minecraft:golden_helmet":2,"minecraft:stick":662,"minecraft:composter":3,"minecraft:oak_fence":29,"minecraft:torch":905,"minecraft:porkchop":22,"minecraft:pointed_dripstone":7,"minecraft:diorite":67,"minecraft:golden_chestplate":1,"minecraft:goat_horn":1,"minecraft:cauldron":53,"minecraft:stone_sword":56,"minecraft:rotten_flesh":834,"minecraft:iron_block":27,"minecraft:blaze_rod":3857,"minecraft:obsidian":91,"minecraft:cobblestone":11435,"minecraft:birch_log":154,"minecraft:pink_petals":19,"minecraft:magma_block":1,"minecraft:feather":22,"minecraft:cooked_beef":276,"minecraft:magma_cream":62,"minecraft:water_bucket":22,"minecraft:andesite":1680,"minecraft:dark_oak_boat":15,"minecraft:beacon":1,"minecraft:potato":66,"minecraft:flint":22,"minecraft:tuff":59,"minecraft:wither_skeleton_skull":5,"minecraft:lapis_lazuli":819,"minecraft:dirt":9533,"minecraft:name_tag":68,"minecraft:glass":93,"minecraft:bone":2871,"minecraft:bow":75,"minecraft:wheat_seeds":252,"minecraft:raw_gold":593,"minecraft:dark_oak_sign":2,"minecraft:mossy_stone_bricks":1,"minecraft:fletching_table":1,"minecraft:diamond_helmet":2,"minecraft:glowstone_dust":66,"minecraft:powered_rail":79,"minecraft:oak_planks":346,"minecraft:cooked_porkchop":435,"minecraft:music_disc_13":1,"minecraft:sand":23,"minecraft:grass_block":11604,"minecraft:dark_oak_log":1215,"minecraft:mossy_cobblestone":5,"minecraft:iron_hoe":7,"minecraft:dispenser":1,"minecraft:deepslate":157,"minecraft:diamond":547,"minecraft:soul_lantern":4,"minecraft:lever":31,"minecraft:cracked_polished_blackstone_bricks":11,"minecraft:crossbow":36,"minecraft:granite":93,"minecraft:golden_apple":10,"minecraft:spruce_sign":44,"minecraft:bread":445,"minecraft:emerald":46,"minecraft:piglin_banner_pattern":1,"minecraft:oak_sapling":100,"minecraft:netherrack":3552,"minecraft:dark_oak_fence":38,"minecraft:nether_star":1,"minecraft:crimson_roots":7,"minecraft:diamond_pickaxe":138,"minecraft:crafting_table":10,"minecraft:azure_bluet":3,"minecraft:chicken":18,"minecraft:nether_wart":235,"minecraft:wooden_pickaxe":3,"minecraft:stone_brick_wall":204,"minecraft:gold_block":198,"minecraft:shield":33,"minecraft:cornflower":4,"minecraft:moss_carpet":2,"minecraft:iron_axe":6,"minecraft:wooden_sword":8,"minecraft:flint_and_steel":10,"minecraft:iron_shovel":1,"minecraft:blackstone":424,"minecraft:creeper_banner_pattern":1,"minecraft:glass_pane":45,"minecraft:deepslate_diamond_ore":38,"minecraft:beef":44,"minecraft:light_gray_wool":1,"minecraft:oak_boat":4,"minecraft:observer":1,"minecraft:copper_ore":319,"minecraft:poppy":4,"minecraft:sugar_cane":71,"minecraft:egg":16,"minecraft:lectern":405,"minecraft:minecart":5,"minecraft:chest":15,"minecraft:birch_sapling":4,"minecraft:piston":9,"minecraft:spruce_trapdoor":13,"minecraft:dark_oak_sapling":9,"minecraft:raw_iron":8826,"minecraft:stone":82999,"minecraft:oak_door":2,"minecraft:polished_blackstone_bricks":69,"minecraft:carrot":232,"minecraft:redstone":29,"minecraft:netherite_pickaxe":15,"minecraft:dark_oak_planks":440,"minecraft:arrow":1565,"minecraft:diamond_chestplate":12,"minecraft:nether_bricks":1530,"minecraft:diamond_boots":12,"minecraft:hay_block":50,"minecraft:saddle":89,"minecraft:gold_ingot":43,"minecraft:mutton":92,"minecraft:skeleton_skull":1,"minecraft:white_wool":44,"minecraft:rail":91,"minecraft:oxeye_daisy":9,"minecraft:netherite_boots":2,"minecraft:basalt":1574,"minecraft:golden_carrot":94,"minecraft:glow_ink_sac":20,"minecraft:leather":128,"minecraft:birch_planks":312,"minecraft:oak_log":1406,"minecraft:ancient_debris":6,"minecraft:golden_boots":1,"minecraft:yellow_bed":4,"minecraft:cobblestone_wall":8,"minecraft:gunpowder":275,"minecraft:cobblestone_stairs":55,"minecraft:sculk_vein":2,"minecraft:paper":54,"minecraft:white_banner":34,"minecraft:cooked_mutton":137,"minecraft:apple":39,"minecraft:stone_bricks":330,"minecraft:kelp":321,"minecraft:iron_ingot":339,"minecraft:stone_pickaxe":3,"minecraft:cooked_chicken":3,"minecraft:iron_ore":30,"minecraft:iron_sword":37,"minecraft:soul_sand":8,"minecraft:dark_oak_stairs":21,"minecraft:book":31,"minecraft:oak_slab":9,"minecraft:nether_quartz_ore":22,"minecraft:dark_oak_slab":20,"minecraft:sweet_berries":267,"minecraft:brush":6,"minecraft:stone_brick_slab":1,"minecraft:quartz":490,"minecraft:dandelion":35,"minecraft:dripstone_block":3,"minecraft:gravel":1811,"minecraft:lava_bucket":1,"minecraft:spruce_sapling":89,"minecraft:blast_furnace":2,"minecraft:white_bed":3,"minecraft:spruce_log":1083,"minecraft:spider_eye":206,"minecraft:diamond_shovel":29,"minecraft:sculk_sensor":68,"minecraft:coal_ore":743,"minecraft:slime_ball":158,"minecraft:stone_axe":12,"minecraft:rib_armor_trim_smithing_template":3,"minecraft:chainmail_leggings":3,"minecraft:iron_helmet":45,"minecraft:diamond_axe":17,"minecraft:mossy_cobblestone_stairs":7,"minecraft:gray_wool":9,"minecraft:baked_potato":3,"minecraft:black_wool":10,"minecraft:coal":5197},"minecraft:mined":{"minecraft:dark_oak_planks":314,"minecraft:sculk_vein":41,"minecraft:cobblestone_stairs":27,"minecraft:obsidian":42,"minecraft:granite":53,"minecraft:grass_block":12201,"minecraft:cracked_polished_blackstone_bricks":3,"minecraft:composter":1,"minecraft:oxeye_daisy":1,"minecraft:nether_wart":19,"minecraft:polished_blackstone_bricks":17,"minecraft:tall_seagrass":1,"minecraft:magma_block":1,"minecraft:glowstone":10,"minecraft:mossy_cobblestone_stairs":4,"minecraft:iron_ore":747,"minecraft:turtle_egg":12,"minecraft:sticky_piston":4,"minecraft:fire":128,"minecraft:cobbled_deepslate":7,"minecraft:moss_carpet":1,"minecraft:deepslate_lapis_ore":15,"minecraft:fletching_table":1,"minecraft:azure_bluet":2,"minecraft:dark_oak_stairs":13,"minecraft:sculk_shrieker":3,"minecraft:pointed_dripstone":3,"minecraft:water_cauldron":4,"minecraft:oak_stairs":1,"minecraft:iron_block":3,"minecraft:piston_head":4,"minecraft:deepslate_redstone_ore":5,"minecraft:blackstone":346,"minecraft:kelp_plant":2,"minecraft:crimson_nylium":1,"minecraft:soul_fire":3,"minecraft:soul_lantern":4,"minecraft:torch":325,"minecraft:blast_furnace":2,"minecraft:beacon":1,"minecraft:chest":8,"minecraft:spruce_wall_sign":3,"minecraft:glass":3,"minecraft:nether_quartz_ore":410,"minecraft:cobblestone":409,"minecraft:oak_planks":20,"minecraft:sugar_cane":27,"minecraft:wall_torch":2,"minecraft:spruce_sign":3,"minecraft:cauldron":4,"minecraft:deepslate_copper_ore":2,"minecraft:pink_petals":7,"minecraft:skeleton_skull":1,"minecraft:seagrass":2,"minecraft:powered_rail":35,"minecraft:dark_oak_slab":27,"minecraft:birch_log":56,"minecraft:oak_log":996,"minecraft:dirt":9505,"minecraft:sand":16,"minecraft:ancient_debris":6,"minecraft:netherrack":5122,"minecraft:piston":6,"minecraft:deepslate":346,"minecraft:oak_leaves":235,"minecraft:nether_gold_ore":19,"minecraft:tuff":21,"minecraft:dark_oak_leaves":6,"minecraft:mossy_cobblestone":12,"minecraft:deepslate_diamond_ore":146,"minecraft:dark_oak_log":753,"minecraft:nether_bricks":403,"minecraft:lever":12,"minecraft:glow_lichen":1,"minecraft:dark_oak_fence":42,"minecraft:crimson_roots":2,"minecraft:spruce_leaves":105,"minecraft:kelp":1,"minecraft:large_fern":26,"minecraft:hay_block":52,"minecraft:furnace":1,"minecraft:carrots":43,"minecraft:andesite":1847,"minecraft:peony":1,"minecraft:gold_block":4,"minecraft:nether_brick_fence":26,"minecraft:deepslate_iron_ore":392,"minecraft:cobblestone_slab":11,"minecraft:rail":30,"minecraft:stone":104395,"minecraft:white_wool":1,"minecraft:oak_slab":4,"minecraft:soul_sand":22,"minecraft:dandelion":5,"minecraft:basalt":1119,"minecraft:observer":1,"minecraft:crafting_table":5,"minecraft:short_grass":604,"minecraft:emerald_ore":2,"minecraft:rose_bush":2,"minecraft:sculk_sensor":21,"minecraft:lectern":365,"minecraft:stone_slab":47,"minecraft:copper_ore":403,"minecraft:tall_grass":131,"minecraft:deepslate_gold_ore":41,"minecraft:sculk":409,"minecraft:diorite":38,"minecraft:birch_planks":172,"minecraft:gray_wool":9,"minecraft:cobblestone_wall":8,"minecraft:sweet_berry_bush":41,"minecraft:ice":2,"minecraft:birch_leaves":7,"minecraft:spruce_log":475,"minecraft:yellow_bed":1,"minecraft:coal_ore":1930,"minecraft:gravel":1561,"minecraft:dripstone_block":2,"minecraft:cobweb":1,"minecraft:stone_bricks":65,"minecraft:gold_ore":10,"minecraft:infested_stone":1,"minecraft:fern":4},"minecraft:killed_by":{"minecraft:wither_skeleton":10,"minecraft:piglin_brute":6,"minecraft:creeper":6,"minecraft:pillager":1,"minecraft:magma_cube":1,"minecraft:vindicator":1,"minecraft:piglin":4,"minecraft:blaze":13,"minecraft:zombie":9,"minecraft:player":1,"minecraft:spider":2,"minecraft:enderman":1,"minecraft:skeleton":23,"minecraft:wither":3}},"DataVersion":3700}